capl_cli/__init__.py
capl_cli/config.py
capl_cli/converters.py
capl_cli/main.py
capl_cli/models.py
capl_formatter/GEMINI.md
capl_formatter/__init__.py
capl_formatter/engine.py
capl_formatter/models.py
capl_formatter/strategies.py
capl_formatter/utils.py
capl_formatter/rules/__init__.py
capl_formatter/rules/base.py
capl_formatter/rules/block_expansion.py
capl_formatter/rules/comments.py
capl_formatter/rules/indentation.py
capl_formatter/rules/quotes.py
capl_formatter/rules/spacing.py
capl_formatter/rules/splitting.py
capl_formatter/rules/structure.py
capl_formatter/rules/switch.py
capl_formatter/rules/top_level_ordering.py
capl_formatter/rules/vertical_spacing.py
capl_formatter/rules/whitespace.py
capl_formatter/rules/wrapping.py
capl_formatter/tests_formatter/__init__.py
capl_formatter/tests_formatter/test_comments.py
capl_formatter/tests_formatter/test_formatting_snapshots.py
capl_formatter/tests_formatter/test_golden_files.py
capl_formatter/tests_formatter/fixtures/expected/comments_comprehensive.can
capl_formatter/tests_formatter/fixtures/expected/enum_complex.can
capl_formatter/tests_formatter/fixtures/expected/ip_endpoint.can
capl_formatter/tests_formatter/fixtures/expected/reorder_complex.can
capl_formatter/tests_formatter/fixtures/expected/struct_basic.can
capl_formatter/tests_formatter/fixtures/expected/switch_nested.can
capl_formatter/tests_formatter/fixtures/expected/vertical_spacing_comprehensive.can
capl_formatter/tests_formatter/fixtures/input/comments_comprehensive.can
capl_formatter/tests_formatter/fixtures/input/enum_complex.can
capl_formatter/tests_formatter/fixtures/input/ip_endpoint.can
capl_formatter/tests_formatter/fixtures/input/reorder_complex.can
capl_formatter/tests_formatter/fixtures/input/struct_basic.can
capl_formatter/tests_formatter/fixtures/input/switch_nested.can
capl_formatter/tests_formatter/fixtures/input/vertical_spacing_comprehensive.can
capllint-0.1.0.dist-info/METADATA
capllint-0.1.0.dist-info/WHEEL
capllint-0.1.0.dist-info/entry_points.txt
capllint-0.1.0.dist-info/RECORD
