Metadata-Version: 2.4
Name: capllint
Version: 0.1.0
Summary: Static analysis and linting tools for CAPL (CANoe Programming Language)
Project-URL: Homepage, https://github.com/MohamedHamed19m/CAPL_Linter
Project-URL: Documentation, https://github.com/MohamedHamed19m/CAPL_Linter#readme
Project-URL: Repository, https://github.com/MohamedHamed19m/CAPL_Linter
Project-URL: Issues, https://github.com/MohamedHamed19m/CAPL_Linter/issues
Author-email: Mohamed Hamed Othman <mohamedahamed1915@gmail.com>
License: MIT
Keywords: automotive,can,canalyzer,canoe,capl,linter,static-analysis
Classifier: Development Status :: 3 - Alpha
Classifier: Intended Audience :: Developers
Classifier: License :: OSI Approved :: MIT License
Classifier: Programming Language :: Python :: 3
Classifier: Programming Language :: Python :: 3.10
Classifier: Programming Language :: Python :: 3.11
Classifier: Programming Language :: Python :: 3.12
Classifier: Topic :: Software Development :: Quality Assurance
Requires-Python: >=3.10
Requires-Dist: pydantic>=2.0.0
Requires-Dist: rich>=13.0.0
Requires-Dist: tree-sitter-c>=0.21.0
Requires-Dist: tree-sitter>=0.21.0
Requires-Dist: typer>=0.9.0
